autoitobfuscator/__init__.py
autoitobfuscator/autoitobfuscator.py
pelock/__init__.py
pelock/autoitobfuscator.py
autoitobfuscator-1.0.4.dist-info/METADATA
autoitobfuscator-1.0.4.dist-info/WHEEL
autoitobfuscator-1.0.4.dist-info/top_level.txt
autoitobfuscator-1.0.4.dist-info/RECORD
