Metadata-Version: 2.1
Name: autoitobfuscator
Version: 1.0.4
Summary: AutoIt Obfuscator Web API interface can help you to protect your AutoIt script source code against analysis, reverse engineering and decompilation. AutoIt Obfuscator provides advanced AutoIt source code parsing based on AST trees, multiple advanced obfuscation strategies are available.
Home-page: https://www.pelock.com
Author: Bartosz Wójcik
Author-email: support@pelock.com
License: Apache-2.0
Keywords: autoit au3 obfuscator obfuscation obfuscate decompile decompiler decompilation antidebug antivm antisandbox antiemulator
Platform: UNKNOWN
Classifier: Development Status :: 5 - Production/Stable
Classifier: Topic :: Software Development :: Libraries :: Python Modules
Classifier: Natural Language :: English
Classifier: License :: OSI Approved :: Apache Software License
Classifier: Programming Language :: Python :: 3
